toil_batch_system_tes/__init__.py
toil_batch_system_tes/tes_batch_system.py
toil_batch_system_tes/test/__init__.py
toil_batch_system_tes/test/test.py
toil_batch_system_tes-2.0.0.dist-info/LICENSE
toil_batch_system_tes-2.0.0.dist-info/METADATA
toil_batch_system_tes-2.0.0.dist-info/WHEEL
toil_batch_system_tes-2.0.0.dist-info/top_level.txt
toil_batch_system_tes-2.0.0.dist-info/RECORD
