Metadata-Version: 2.1
Name: toil_batch_system_tes
Version: 2.0.0
Summary: A TES batch system plugin for Toil
Author-email: Adam Novak <anovak@soe.ucsc.edu>
Project-URL: Homepage, https://github.com/adamnovak/toil_batch_system_tes
Classifier: Programming Language :: Python :: 3
Requires-Python: >=3.8
License-File: LICENSE
Requires-Dist: toil[aws] <8,>=7.0
Requires-Dist: py-tes <1,>=0.4.2
Requires-Dist: pytest <10,>=8.2.2
Requires-Dist: pytest-cov <6,>=2.12.1
Requires-Dist: pytest-timeout <3,>=1.4.2
Requires-Dist: pytest-xdist
